README.md
setup.py
unmango_pulumi_pihole/__init__.py
unmango_pulumi_pihole/_utilities.py
unmango_pulumi_pihole/ad_blocker_status.py
unmango_pulumi_pihole/cname_record.py
unmango_pulumi_pihole/dns_record.py
unmango_pulumi_pihole/get_cname_records.py
unmango_pulumi_pihole/get_dns_records.py
unmango_pulumi_pihole/get_domains.py
unmango_pulumi_pihole/get_groups.py
unmango_pulumi_pihole/group.py
unmango_pulumi_pihole/outputs.py
unmango_pulumi_pihole/provider.py
unmango_pulumi_pihole/pulumi-plugin.json
unmango_pulumi_pihole/py.typed
unmango_pulumi_pihole.egg-info/PKG-INFO
unmango_pulumi_pihole.egg-info/SOURCES.txt
unmango_pulumi_pihole.egg-info/dependency_links.txt
unmango_pulumi_pihole.egg-info/not-zip-safe
unmango_pulumi_pihole.egg-info/requires.txt
unmango_pulumi_pihole.egg-info/top_level.txt
unmango_pulumi_pihole/config/__init__.py
unmango_pulumi_pihole/config/vars.py