Metadata-Version: 2.1
Name: unmango-pulumi-pihole
Version: 0.2.2
Summary: A Pulumi package for creating and managing Pi-hole resources
Home-page: https://github.com/unmango/pulumi-pihole
License: Apache-2.0
Project-URL: Repository, https://github.com/unmango/pulumi-pihole
Keywords: pulumi pihole category/network
Platform: UNKNOWN
Requires-Python: >=3.9
